faceware/__init__.py
faceware/pyportal/__init__.py
faceware/pyportal/api_requests.py
faceware/pyportal/base_component.py
faceware/pyportal/constant.py
faceware/pyportal/exceptions.py
faceware/pyportal/job.py
faceware/pyportal/job_result.py
faceware/pyportal/multipart_uploader.py
faceware/pyportal/project.py
faceware/pyportal/utils.py
faceware_pyportal-1.1.1.dist-info/LICENSE
faceware_pyportal-1.1.1.dist-info/METADATA
faceware_pyportal-1.1.1.dist-info/WHEEL
faceware_pyportal-1.1.1.dist-info/RECORD
