Metadata-Version: 2.1
Name: faceware-pyportal
Version: 1.1.1
Summary: Allow programmatic access to Faceware Cloud Portal via Python library
Home-page: https://facewaretech.com/
License: MIT
Author: Faceware Dev Team
Author-email: dev@facewaretech.com
Maintainer: Alex Udrescu
Maintainer-email: alex.udrescu@image-metrics.com
Requires-Python: >=3.8,<4.0
Classifier: License :: OSI Approved :: MIT License
Classifier: Programming Language :: Python :: 3
Classifier: Programming Language :: Python :: 3.8
Classifier: Programming Language :: Python :: 3.9
Classifier: Programming Language :: Python :: 3.10
Classifier: Programming Language :: Python :: 3.11
Requires-Dist: aiohttp (>=3.10.11,<4.0.0)
Requires-Dist: aiolimiter (>=1.1.0,<2.0.0)
Requires-Dist: asyncio (>=3.4.3,<4.0.0)
Requires-Dist: pydantic (>=2.10.2,<3.0.0)
Requires-Dist: setuptools (>=65,<80.9.1) ; python_version >= "3.12"
Requires-Dist: tenacity (>=8.3.0,<9.0.0)
Requires-Dist: tomlkit (>=0.12.5,<0.13.0)
Project-URL: Documentation, https://docs.facewaretech.com/
